pytlsd.cp310-win_amd64.pyd
pytlsd-0.0.2.dist-info/LICENSE
pytlsd-0.0.2.dist-info/METADATA
pytlsd-0.0.2.dist-info/WHEEL
pytlsd-0.0.2.dist-info/top_level.txt
pytlsd-0.0.2.dist-info/RECORD
